LICENSE
MANIFEST.in
README.md
requirements.txt
setup.py
pyauto/__init__.py
pyauto.vault.egg-info/PKG-INFO
pyauto.vault.egg-info/SOURCES.txt
pyauto.vault.egg-info/dependency_links.txt
pyauto.vault.egg-info/requires.txt
pyauto.vault.egg-info/top_level.txt
pyauto/vault/__init__.py
pyauto/vault/commands.py
pyauto/vault/config.py