Metadata-Version: 1.0
Name: pyauto.vault
Version: 0.0.2
Summary: A tool for accessing paths and keys from Vault
Home-page: https://github.com/adamjaso/pyauto/tree/master/vault
Author: Adam Jaso
Author-email: UNKNOWN
License: GNU General Public License V2
Platform: UNKNOWN
